moodlews/__init__.py
moodlews/service.py
welearnbot/__init__.py
welearnbot/__main__.py
welearnbot/action_handlers.py
welearnbot/constants.py
welearnbot/gcal.py
welearnbot/parser.py
welearnbot/resolvers.py
welearnbot/utils.py
welearnbot/welearnbot.py
welearn_bot_iiserkol-1.3.1.dist-info/LICENSE
welearn_bot_iiserkol-1.3.1.dist-info/METADATA
welearn_bot_iiserkol-1.3.1.dist-info/WHEEL
welearn_bot_iiserkol-1.3.1.dist-info/entry_points.txt
welearn_bot_iiserkol-1.3.1.dist-info/top_level.txt
welearn_bot_iiserkol-1.3.1.dist-info/RECORD
