Metadata-Version: 2.1
Name: welearn-bot-iiserkol
Version: 1.3.1
Summary: A command line client for WeLearn, in the IISER Kolkata domain
Home-page: https://github.com/ParthBibekar/Welearn-bot
Author: Parth Bibekar
Author-email: bibekarparth24@gmail.com
License: MIT
License-File: LICENSE
Requires-Dist: beautifulsoup4 (>=4.10.0)
Requires-Dist: google-api-python-client (>=2.36.0)
Requires-Dist: google-auth-oauthlib (>=0.4.4)
Requires-Dist: protobuf (>=3.19.4)
Requires-Dist: requests (>=2.26.0)
